visualacuity-0.1.0a9.dist-info/METADATA
visualacuity-0.1.0a9.dist-info/WHEEL
visualacuity-0.1.0a9.dist-info/licenses/LICENSE
visualacuity/cli/examples/data_quality.py
visualacuity/cli/examples/near_total_loss.py
visualacuity/cli/examples/plus_minus.py
visualacuity/cli/examples/unexpected_patterns.py
visualacuity/cli/examples/va_distribution.py
visualacuity/cli/examples/visit_stats.py
visualacuity/cli/examples/__init__.py
visualacuity/cli/_helpers.py
visualacuity/cli/_map_reduce.py
visualacuity/cli/_stats.py
visualacuity/cli/__init__.py
visualacuity/_enum_helpers.py
visualacuity/_lib.pyi
visualacuity/_parse.py
visualacuity/_read_file.py
visualacuity/_types.py
visualacuity/__init__.py
visualacuity/_lib.pyd
visualacuity-0.1.0a9.dist-info/RECORD
